llama_index/embeddings/ollama/__init__.py
llama_index/embeddings/ollama/base.py
llama_index_embeddings_ollama-0.8.2.dist-info/METADATA
llama_index_embeddings_ollama-0.8.2.dist-info/WHEEL
llama_index_embeddings_ollama-0.8.2.dist-info/licenses/LICENSE
llama_index_embeddings_ollama-0.8.2.dist-info/RECORD
