Metadata-Version: 2.4
Name: llama-index-embeddings-ollama
Version: 0.8.2
Summary: llama-index embeddings ollama integration
Author-email: Your Name <you@example.com>
License-Expression: MIT
License-File: LICENSE
Requires-Python: <4.0,>=3.9
Requires-Dist: llama-index-core<0.14,>=0.13.0
Requires-Dist: ollama>=0.3.1
Requires-Dist: pytest-asyncio>=0.23.8
